autogluon_contrib_nlp/__init__.py
autogluon_contrib_nlp/attention_cell.py
autogluon_contrib_nlp/base.py
autogluon_contrib_nlp/initializer.py
autogluon_contrib_nlp/layers.py
autogluon_contrib_nlp/loss.py
autogluon_contrib_nlp/lr_scheduler.py
autogluon_contrib_nlp/op.py
autogluon_contrib_nlp/registry.py
autogluon_contrib_nlp/sequence_sampler.py
autogluon_contrib_nlp/data/__init__.py
autogluon_contrib_nlp/data/batchify.py
autogluon_contrib_nlp/data/filtering.py
autogluon_contrib_nlp/data/loading.py
autogluon_contrib_nlp/data/sampler.py
autogluon_contrib_nlp/data/vocab.py
autogluon_contrib_nlp/data/tokenizers/__init__.py
autogluon_contrib_nlp/data/tokenizers/base.py
autogluon_contrib_nlp/data/tokenizers/huggingface.py
autogluon_contrib_nlp/data/tokenizers/jieba.py
autogluon_contrib_nlp/data/tokenizers/moses.py
autogluon_contrib_nlp/data/tokenizers/sentencepiece.py
autogluon_contrib_nlp/data/tokenizers/spacy.py
autogluon_contrib_nlp/data/tokenizers/subword_nmt.py
autogluon_contrib_nlp/data/tokenizers/whitespace.py
autogluon_contrib_nlp/data/tokenizers/yttm.py
autogluon_contrib_nlp/models/__init__.py
autogluon_contrib_nlp/models/albert.py
autogluon_contrib_nlp/models/bert.py
autogluon_contrib_nlp/models/electra.py
autogluon_contrib_nlp/models/mobilebert.py
autogluon_contrib_nlp/models/roberta.py
autogluon_contrib_nlp/models/transformer.py
autogluon_contrib_nlp/models/model_zoo_checksums/albert.txt
autogluon_contrib_nlp/models/model_zoo_checksums/bert.txt
autogluon_contrib_nlp/models/model_zoo_checksums/electra.txt
autogluon_contrib_nlp/models/model_zoo_checksums/mobilebert.txt
autogluon_contrib_nlp/models/model_zoo_checksums/roberta.txt
autogluon_contrib_nlp/optimizers/__init__.py
autogluon_contrib_nlp/optimizers/adamw.py
autogluon_contrib_nlp/third_party/__init__.py
autogluon_contrib_nlp/third_party/sentencepiece_model_pb2.py
autogluon_contrib_nlp/third_party/sentencepiece_pb2.py
autogluon_contrib_nlp/utils/__init__.py
autogluon_contrib_nlp/utils/config.py
autogluon_contrib_nlp-0.0.1b20220208.dist-info/LICENSE
autogluon_contrib_nlp-0.0.1b20220208.dist-info/METADATA
autogluon_contrib_nlp-0.0.1b20220208.dist-info/WHEEL
autogluon_contrib_nlp-0.0.1b20220208.dist-info/top_level.txt
autogluon_contrib_nlp-0.0.1b20220208.dist-info/zip-safe
autogluon_contrib_nlp-0.0.1b20220208.dist-info/RECORD
