Metadata-Version: 2.1
Name: autogluon-contrib-nlp
Version: 0.0.1b20220208
Summary: MXNet GluonNLP Toolkit (DeepNumpy Version)
Home-page: https://github.com/sxjscience/autogluon-contrib-nlp
Author: GluonNLP Toolkit Contributors
Author-email: gluonnlp-dev@amazon.com
License: Apache-2.0
Platform: UNKNOWN
Requires-Python: >=3.6
License-File: LICENSE
Requires-Dist: numpy
Requires-Dist: sacremoses (>=0.0.38)
Requires-Dist: yacs (>=0.1.6)
Requires-Dist: sacrebleu
Requires-Dist: flake8
Requires-Dist: regex
Requires-Dist: contextvars
Requires-Dist: pyarrow
Requires-Dist: tokenizers (>=0.9.4)
Requires-Dist: protobuf
Requires-Dist: sentencepiece (==0.1.95)
Requires-Dist: pandas
Provides-Extra: dev
Requires-Dist: pytest ; extra == 'dev'
Requires-Dist: pytest-env ; extra == 'dev'
Requires-Dist: pylint ; extra == 'dev'
Requires-Dist: pylint-quotes ; extra == 'dev'
Requires-Dist: flake8 ; extra == 'dev'
Requires-Dist: recommonmark ; extra == 'dev'
Requires-Dist: sphinx-gallery ; extra == 'dev'
Requires-Dist: sphinx-rtd-theme ; extra == 'dev'
Requires-Dist: mxtheme ; extra == 'dev'
Requires-Dist: sphinx-autodoc-typehints ; extra == 'dev'
Requires-Dist: nbsphinx ; extra == 'dev'
Requires-Dist: flaky ; extra == 'dev'
Provides-Extra: extras
Requires-Dist: boto3 ; extra == 'extras'
Requires-Dist: tqdm ; extra == 'extras'
Requires-Dist: jieba ; extra == 'extras'
Requires-Dist: subword-nmt ; extra == 'extras'
Requires-Dist: youtokentome (>=1.0.6) ; extra == 'extras'
Requires-Dist: spacy (>=2.0.0) ; extra == 'extras'
Requires-Dist: fasttext (>=0.9.2) ; extra == 'extras'
Requires-Dist: langid ; extra == 'extras'
Requires-Dist: nltk ; extra == 'extras'
Requires-Dist: h5py (>=2.10) ; extra == 'extras'
Requires-Dist: scipy ; extra == 'extras'
